seerapi/__init__.py
seerapi/_client.py
seerapi/_client.pyi
seerapi/_model_map.py
seerapi/_models.py
seerapi/_typing.py
seerapi-103.2.0.dist-info/licenses/LICENSE
seerapi-103.2.0.dist-info/METADATA
seerapi-103.2.0.dist-info/WHEEL
seerapi-103.2.0.dist-info/top_level.txt
seerapi-103.2.0.dist-info/RECORD
