Metadata-Version: 2.4
Name: seerapi
Version: 103.2.0
Summary: SeerAPI Python Client
Author-email: Nattsu39 <Nattsu39@outlook.com>
License: MIT License
Project-URL: Homepage, https://github.com/SeerAPI/seerapi-python
Project-URL: Repository, https://github.com/SeerAPI/seerapi-python
Keywords: seerapi,client
Classifier: Operating System :: OS Independent
Classifier: Intended Audience :: Developers
Classifier: License :: OSI Approved :: MIT License
Classifier: Programming Language :: Python :: 3.10
Classifier: Programming Language :: Python :: 3.11
Classifier: Programming Language :: Python :: 3.12
Classifier: Programming Language :: Python :: 3.13
Classifier: Programming Language :: Python :: 3.14
Requires-Python: >=3.10
License-File: LICENSE
Requires-Dist: hishel[httpx]>=1.1.5
Requires-Dist: httpx>=0.28.1
Requires-Dist: seerapi-models<104.0.0,>=103.2.0
Requires-Dist: typing-extensions>=4.15.0
Dynamic: license-file
